proxypool/__init__.py
proxypool-0.0.0.dev0.dist-info/DESCRIPTION.rst
proxypool-0.0.0.dev0.dist-info/METADATA
proxypool-0.0.0.dev0.dist-info/RECORD
proxypool-0.0.0.dev0.dist-info/WHEEL
proxypool-0.0.0.dev0.dist-info/metadata.json
proxypool-0.0.0.dev0.dist-info/top_level.txt
