Metadata-Version: 2.0
Name: proxypool
Version: 0.0.0.dev0
Summary: A proxy poll: get free and high quality proxies
Home-page: https://github.com/franklingu/proxypool
Author: franklingu
Author-email: franklingujunchao@gmail.com
License: MIT
Keywords: proxy pool free collector
Platform: UNKNOWN
Classifier: Programming Language :: Python :: 3.5
Classifier: Programming Language :: Python :: 3.6
Classifier: Programming Language :: Python
Classifier: Development Status :: 3 - Alpha
Classifier: Intended Audience :: Developers
Requires-Python: >=3.5, <4
Requires-Dist: lxml (>=3.7.3)
Requires-Dist: requests (>=2.13.0)
